pibooth_oled_display/__init__.py
pibooth_oled_display/pibooth_oled_display.py
pibooth_oled_display/oled_display/Date-Time_Format_Codes.rst
pibooth_oled_display/oled_display/pibooth_oled_display_2.py
pibooth_oled_display/oled_display/default/Default_DejaVuSerif-Bold.ttf
pibooth_oled_display/oled_display/default/default_logo.png
pibooth_oled_display/oled_display/fonts/Cantarell-Bold.otf
pibooth_oled_display/oled_display/fonts/Cantarell-ExtraBold.otf
pibooth_oled_display/oled_display/fonts/Cantarell-Light.otf
pibooth_oled_display/oled_display/fonts/Cantarell-Regular.otf
pibooth_oled_display/oled_display/fonts/Cantarell-Thin.otf
pibooth_oled_display/oled_display/fonts/DejaVuMathTeXGyre.ttf
pibooth_oled_display/oled_display/fonts/DejaVuSans-Bold.ttf
pibooth_oled_display/oled_display/fonts/DejaVuSans-BoldOblique.ttf
pibooth_oled_display/oled_display/fonts/DejaVuSans-ExtraLight.ttf
pibooth_oled_display/oled_display/fonts/DejaVuSans-Oblique.ttf
pibooth_oled_display/oled_display/fonts/DejaVuSans.ttf
pibooth_oled_display/oled_display/fonts/DejaVuSansCondensed-Bold.ttf
pibooth_oled_display/oled_display/fonts/DejaVuSansCondensed-BoldOblique.ttf
pibooth_oled_display/oled_display/fonts/DejaVuSansCondensed-Oblique.ttf
pibooth_oled_display/oled_display/fonts/DejaVuSansCondensed.ttf
pibooth_oled_display/oled_display/fonts/DejaVuSansMono-Bold.ttf
pibooth_oled_display/oled_display/fonts/DejaVuSansMono-BoldOblique.ttf
pibooth_oled_display/oled_display/fonts/DejaVuSansMono-Oblique.ttf
pibooth_oled_display/oled_display/fonts/DejaVuSansMono.ttf
pibooth_oled_display/oled_display/fonts/DejaVuSerif-Bold.ttf
pibooth_oled_display/oled_display/fonts/DejaVuSerif-BoldItalic.ttf
pibooth_oled_display/oled_display/fonts/DejaVuSerif-Italic.ttf
pibooth_oled_display/oled_display/fonts/DejaVuSerif.ttf
pibooth_oled_display/oled_display/fonts/DejaVuSerifCondensed-Bold.ttf
pibooth_oled_display/oled_display/fonts/DejaVuSerifCondensed-BoldItalic.ttf
pibooth_oled_display-2.0.3.dist-info/LICENSE
pibooth_oled_display-2.0.3.dist-info/METADATA
pibooth_oled_display-2.0.3.dist-info/WHEEL
pibooth_oled_display-2.0.3.dist-info/entry_points.txt
pibooth_oled_display-2.0.3.dist-info/top_level.txt
pibooth_oled_display-2.0.3.dist-info/RECORD
