Metadata-Version: 2.1
Name: pibooth-oled-display
Version: 2.0.3
Summary: Pibooth Plugin to manage small OLED displays (via I2c or SPI). Show various counters (e.g., photos taken), display time-date, text, logos, and animated GIFs.
Home-page: https://github.com/DJ-Dingo/pibooth-oled-display
Download-URL: https://github.com/DJ-Dingo/pibooth-oled-display/archive/2.0.3.tar.gz
Author: Kenneth Nicholas Jørgensen
License: GPLv3
Keywords: raspberry pi,camera,raspberry pi camera,photobooth,selfiecam,pygame,pil,pillow,pibooth,pibooth plugin,oled display,luma.oled,oled
Platform: unix
Platform: linux
Classifier: Development Status :: 5 - Production/Stable
Classifier: Environment :: Plugins
Classifier: Intended Audience :: Developers
Classifier: Intended Audience :: End Users/Desktop
Classifier: License :: OSI Approved :: GNU Affero General Public License v3
Classifier: Natural Language :: English
Classifier: Operating System :: POSIX :: Linux
Classifier: Programming Language :: Python :: 3.6
Classifier: Programming Language :: Python :: 3.7
Classifier: Programming Language :: Python :: 3.8
Classifier: Programming Language :: Python :: 3.9
Classifier: Topic :: Multimedia :: Graphics :: Capture :: Digital Camera
Requires-Python: >=3.6
License-File: LICENSE
Requires-Dist: pibooth (>=2.0.3)
Requires-Dist: luma.oled (>=3.12.0)
Requires-Dist: setuptools
